unipka/__init__.py
unipka/assets.py
unipka/unipka.py
unipka/version.py
unipka/_internal/__init__.py
unipka/_internal/conformer.py
unipka/_internal/coordinates.py
unipka/_internal/dataset.py
unipka/_internal/dict.py
unipka/_internal/draw.py
unipka/_internal/solvation.py
unipka/_internal/template.py
unipka/_internal/widget.py
unipka/_internal/model/__init__.py
unipka/_internal/model/transformer.py
unipka/_internal/model/unimol.py
unipka/_internal/model/utils.py
unipka/data/simple_smarts_pattern.tsv
unipka/data/smarts_pattern.tsv
unipka/data/weights.kpuu.npz
unipka-0.2.0.dist-info/licenses/LICENSE
unipka-0.2.0.dist-info/METADATA
unipka-0.2.0.dist-info/WHEEL
unipka-0.2.0.dist-info/top_level.txt
unipka-0.2.0.dist-info/RECORD
