Metadata-Version: 2.4
Name: unipka
Version: 0.2.0
Summary: Unoffical wrapper around UnipKa
Author: Finlay MacLean
License: MIT
License-File: LICENSE
Requires-Dist: requests
Requires-Dist: platformdirs
Requires-Dist: scipy
Requires-Dist: numpy
Requires-Dist: pandas
Requires-Dist: seaborn
Requires-Dist: torch>2.3.0
Requires-Dist: rdkit
Requires-Dist: anywidget
Requires-Dist: matplotlib
Requires-Dist: scikit-learn
Dynamic: license-file
